fbuild/__init__.py
fbuild/cli.py
fbuild/cli_utils.py
fbuild/interrupt_utils.py
fbuild/output.py
fbuild/py.typed
fbuild/subprocess_utils.py
fbuild/api/__init__.py
fbuild/api/serial_monitor.py
fbuild/api/serial_monitor_file.py
fbuild/assets/example.txt
fbuild/build/__init__.py
fbuild/build/archive_creator.py
fbuild/build/binary_generator.py
fbuild/build/build_component_factory.py
fbuild/build/build_info_generator.py
fbuild/build/build_state.py
fbuild/build/build_utils.py
fbuild/build/compilation_executor.py
fbuild/build/compiler.py
fbuild/build/compiler_avr.py
fbuild/build/configurable_compiler.py
fbuild/build/configurable_linker.py
fbuild/build/flag_builder.py
fbuild/build/library_dependency_processor.py
fbuild/build/linker.py
fbuild/build/orchestrator.py
fbuild/build/orchestrator_avr.py
fbuild/build/orchestrator_esp32.py
fbuild/build/orchestrator_rp2040.py
fbuild/build/orchestrator_stm32.py
fbuild/build/orchestrator_teensy.py
fbuild/build/psram_utils.py
fbuild/build/source_compilation_orchestrator.py
fbuild/build/source_scanner.py
fbuild/config/__init__.py
fbuild/config/board_config.py
fbuild/config/board_loader.py
fbuild/config/ini_parser.py
fbuild/config/mcu_specs.py
fbuild/daemon/__init__.py
fbuild/daemon/api.py
fbuild/daemon/async_client.py
fbuild/daemon/async_protocol.py
fbuild/daemon/async_server.py
fbuild/daemon/cancellation.py
fbuild/daemon/compilation_queue.py
fbuild/daemon/configuration_lock.py
fbuild/daemon/connection.py
fbuild/daemon/connection_registry.py
fbuild/daemon/daemon.py
fbuild/daemon/daemon_context.py
fbuild/daemon/device_discovery.py
fbuild/daemon/device_manager.py
fbuild/daemon/error_collector.py
fbuild/daemon/fastapi_app.py
fbuild/daemon/file_cache.py
fbuild/daemon/firmware_ledger.py
fbuild/daemon/lock_manager.py
fbuild/daemon/lock_types.py
fbuild/daemon/logging_utils.py
fbuild/daemon/message_protocol.py
fbuild/daemon/operation_registry.py
fbuild/daemon/paths.py
fbuild/daemon/port_state_manager.py
fbuild/daemon/process_tracker.py
fbuild-1.3.35.dist-info/licenses/LICENSE
fbuild-1.3.35.dist-info/METADATA
fbuild-1.3.35.dist-info/WHEEL
fbuild-1.3.35.dist-info/entry_points.txt
fbuild-1.3.35.dist-info/top_level.txt
fbuild-1.3.35.dist-info/RECORD
