Metadata-Version: 2.4
Name: fbuild
Version: 1.3.35
Summary: Modern replacement for PlatformIO with URL-based platform/toolchain management and bug-free architecture
Home-page: https://github.com/fastled/fbuild
Maintainer: Zachary Vorhies
License: BSD 3-Clause License
Keywords: embedded,arduino,platformio,compiler,toolchain,firmware,microcontroller
Classifier: Programming Language :: Python :: 3
Requires-Python: >=3.10
License-File: LICENSE
Requires-Dist: requests>=2.28.0
Requires-Dist: tqdm>=4.64.0
Requires-Dist: pyserial>=3.5
Requires-Dist: esptool>=4.6.0
Requires-Dist: psutil>=5.9.0
Requires-Dist: fasteners>=0.18
Requires-Dist: fastapi>=0.109.0
Requires-Dist: uvicorn[standard]>=0.27.0
Requires-Dist: websockets>=12.0
Requires-Dist: httpx>=0.26.0
Requires-Dist: pydantic>=2.0.0
Provides-Extra: dev
Requires-Dist: pytest<9.0,>=7.0; extra == "dev"
Requires-Dist: pytest-cov; extra == "dev"
Requires-Dist: pytest-xdist; extra == "dev"
Dynamic: home-page
Dynamic: license-file
Dynamic: maintainer
